jhalog/__init__.py
jhalog/_backends/__init__.py
jhalog/_backends/_cloudwatch_logs.py
jhalog/_backends/cloudwatch_logs_async.py
jhalog/_backends/logging.py
jhalog/_backends/stdout.py
jhalog/_base.py
jhalog/_base_async.py
jhalog/_base_thread.py
jhalog/_common.py
jhalog/_event.py
jhalog/exception_handlers/__init__.py
jhalog/exception_handlers/botocore.py
jhalog/exceptions.py
jhalog/py.typed
jhalog/typing.py
jhalog-0.1.10.dist-info/LICENSE
jhalog-0.1.10.dist-info/WHEEL
jhalog-0.1.10.dist-info/METADATA
jhalog-0.1.10.dist-info/RECORD
